mo_streams/__init__.py
mo_streams/_utils.py
mo_streams/byte_stream.py
mo_streams/empty_stream.py
mo_streams/files.py
mo_streams/function_factory.py
mo_streams/object_stream.py
mo_streams/string_stream.py
mo_streams/type_parser.py
mo_streams/type_utils.py
mo_streams-1.681.25075.dist-info/LICENSE
mo_streams-1.681.25075.dist-info/METADATA
mo_streams-1.681.25075.dist-info/WHEEL
mo_streams-1.681.25075.dist-info/top_level.txt
mo_streams-1.681.25075.dist-info/RECORD
