Metadata-Version: 2.2
Name: mo-streams
Version: 1.681.25075
Summary: More Streams! Chained function calls
Home-page: https://github.com/klahnakoski/mo-streams
Author: Kyle Lahnakoski
Author-email: kyle@lahnakoski.com
License: MPL 2.0
Classifier: Development Status :: 3 - Alpha
Classifier: Topic :: Software Development :: Libraries
Classifier: Topic :: Software Development :: Libraries :: Python Modules
Classifier: License :: OSI Approved :: Mozilla Public License 2.0 (MPL 2.0)
Classifier: Programming Language :: Python :: 3.8
Classifier: Programming Language :: Python :: 3.9
Classifier: Programming Language :: Python :: 3.10
Classifier: Programming Language :: Python :: 3.11
Classifier: Programming Language :: Python :: 3.12
Classifier: Programming Language :: Python :: 3.13
License-File: LICENSE
Requires-Dist: mo-dots==10.678.25061
Requires-Dist: mo-files==6.681.25075
Requires-Dist: mo-future==7.678.25061
Requires-Dist: mo-json==6.679.25061
Provides-Extra: tests
Requires-Dist: mo-files>=6.679.25061; extra == "tests"
Requires-Dist: mo-logs>=8.678.25061; extra == "tests"
Requires-Dist: zstandard>=0.23.0; extra == "tests"
Requires-Dist: boto3>=1.37.4; extra == "tests"
Requires-Dist: moto>=5.0.28; extra == "tests"
Requires-Dist: pandas>=2.0.3; extra == "tests"
Requires-Dist: mo-threads>=6.679.25061; extra == "tests"
Requires-Dist: mo-testing>=8.674.25037; extra == "tests"
Requires-Dist: mo-threads>=6.679.25061; extra == "tests"
Requires-Dist: cffi>=1.17.1; extra == "tests"
Dynamic: author
Dynamic: author-email
Dynamic: classifier
Dynamic: description
Dynamic: description-content-type
Dynamic: home-page
Dynamic: license
Dynamic: provides-extra
Dynamic: requires-dist
Dynamic: summary
